bolt/__init__.py
bolt/bolt_router.py
bolt_sdk_py2-1.0.5.dist-info/LICENSE
bolt_sdk_py2-1.0.5.dist-info/METADATA
bolt_sdk_py2-1.0.5.dist-info/WHEEL
bolt_sdk_py2-1.0.5.dist-info/top_level.txt
bolt_sdk_py2-1.0.5.dist-info/RECORD
