Metadata-Version: 2.1
Name: bolt-sdk-py2
Version: 1.0.5
Summary: Bolt Python SDK
Home-page: https://github.com/projectn-oss/projectn-bolt-python2
Author: Project N
License: UNKNOWN
Platform: UNKNOWN
Classifier: Programming Language :: Python :: 2
Classifier: Operating System :: OS Independent
Classifier: License :: OSI Approved :: Apache Software License
Classifier: Topic :: Software Development :: Libraries
Requires-Python: >=2.7
Requires-Dist: boto3
Requires-Dist: botocore
